replytics/__init__.py
replytics-0.2.0.dist-info/LICENCE
replytics-0.2.0.dist-info/METADATA
replytics-0.2.0.dist-info/WHEEL
replytics-0.2.0.dist-info/top_level.txt
replytics-0.2.0.dist-info/RECORD
