Metadata-Version: 2.1
Name: replytics
Version: 0.2.0
Summary: Easily track your statistics for Repl.it projects!
Home-page: https://replytics.matdoes.dev
Author: mat
Author-email: pypi@matdoes.dev
License: UNKNOWN
Platform: UNKNOWN
Classifier: Programming Language :: Python :: 3
Classifier: License :: OSI Approved :: MIT License
Classifier: Operating System :: OS Independent
Requires-Dist: websocket-client
